ignorant/__init__.py
ignorant/core.py
ignorant/instruments.py
ignorant/localuseragent.py
ignorant/modules/__init__.py
ignorant/modules/shopping/__init__.py
ignorant/modules/shopping/amazon.py
ignorant/modules/social_media/__init__.py
ignorant/modules/social_media/instagram.py
ignorant/modules/social_media/snapchat.py
ignorant-1.2.dist-info/LICENSE
ignorant-1.2.dist-info/METADATA
ignorant-1.2.dist-info/WHEEL
ignorant-1.2.dist-info/entry_points.txt
ignorant-1.2.dist-info/top_level.txt
ignorant-1.2.dist-info/RECORD
