Metadata-Version: 2.1
Name: ignorant
Version: 1.2
Summary: ignorant allows you to check if a phone is used on different sites like snapchat.
Home-page: http://github.com/megadose/ignorant
Author: megadose
Author-email: megadose@protonmail.com
License: UNKNOWN
Platform: UNKNOWN
Classifier: Programming Language :: Python
Classifier: License :: OSI Approved :: GNU General Public License v3 (GPLv3)
Requires-Dist: argparse
Requires-Dist: bs4
Requires-Dist: httpx
Requires-Dist: termcolor
Requires-Dist: tqdm
Requires-Dist: trio
